[
  {
    "title": "Onion Architecture",
    "creator": "Ritesh Kapoor",
    "link": "https://medium.com/expedia-group-tech/onion-architecture-deed8a554423?source=rss----38998a53046f---4",
    "date": "Jul 12, 2022",
    "imageUrl": "https://cdn-images-1.medium.com/max/1024/0*h2vnCinMat3lh9ix"
  },
  {
    "title": "Error Budget Policies in Practice",
    "creator": "Eric Trang",
    "link": "https://medium.com/expedia-group-tech/error-budget-policies-in-practice-4c98f56a28c1?source=rss----38998a53046f---4",
    "date": "Jul 5, 2022",
    "imageUrl": "https://cdn-images-1.medium.com/max/1024/1*dI7DI5ZnSjLPEV0_QY5KLA.jpeg"
  },
  {
    "title": "Error Budget Policy Adoption at Expedia Group",
    "creator": "Lasantha Kularatne",
    "link": "https://medium.com/expedia-group-tech/error-budget-policy-adoption-at-expedia-group-7d80d41c4a8b?source=rss----38998a53046f---4",
    "date": "Jun 28, 2022",
    "imageUrl": "https://cdn-images-1.medium.com/max/1024/1*4NDLe4oRhudBJBfe7retmw.jpeg"
  },
  {
    "title": "Managing a federated Kubernetes Cluster using Kubefed v2",
    "creator": "Aditya Sharma",
    "link": "https://medium.com/expedia-group-tech/managing-a-federated-kubernetes-cluster-using-kubefed-v2-5f115dbdbe05?source=rss----38998a53046f---4",
    "date": "Jun 21, 2022",
    "imageUrl": "https://cdn-images-1.medium.com/max/1024/1*5S22_CcU4CH9mZbzwRSg5Q.jpeg"
  },
  {
    "title": "Centralizing GraphQL Mock Data to an Internal Route",
    "creator": "Adam Schutte",
    "link": "https://medium.com/expedia-group-tech/centralizing-graphql-mock-data-to-an-internal-route-e17adbe4002f?source=rss----38998a53046f---4",
    "date": "Jun 14, 2022",
    "imageUrl": "https://cdn-images-1.medium.com/max/1000/0*IVbOg6nUeQLde_j7"
  },
  {
    "title": "Lightning Fast Flight Searches on Expedia using Apache Ignite — Part II",
    "creator": "Bhanu Choudhary",
    "link": "https://medium.com/expedia-group-tech/lightning-fast-flight-searches-on-expedia-using-apache-ignite-part-ii-7fc7e3bca7f?source=rss----38998a53046f---4",
    "date": "Jun 9, 2022",
    "imageUrl": "https://cdn-images-1.medium.com/max/1024/1*3_9lmHH0CMVJyA873nrbMg.jpeg"
  },
  {
    "title": "Asynchronous Testing with Combine Schedulers",
    "creator": "Francisco José Belchí Martínez",
    "link": "https://medium.com/expedia-group-tech/asynchronous-testing-with-combine-schedulers-5dc9c45f56dd?source=rss----38998a53046f---4",
    "date": "Jun 7, 2022",
    "imageUrl": "https://cdn-images-1.medium.com/max/1024/1*l81bif_i58nefp0pwgAw5Q.jpeg"
  },
  {
    "title": "How Vrbo and Expedia Lodging Prepared for 2022’s Super Bowl LVI",
    "creator": "Juliette Howland",
    "link": "https://medium.com/expedia-group-tech/how-vrbo-and-expedia-lodging-prepared-for-2022s-super-bowl-lvi-984e8d4f2faa?source=rss----38998a53046f---4",
    "date": "May 31, 2022",
    "imageUrl": "https://cdn-images-1.medium.com/max/1024/1*qF-iXwrR3tlD1-u_XXB9bg.jpeg"
  },
  {
    "title": "Software Architectural Patterns in Data Engineering",
    "creator": "Kunal Sharma",
    "link": "https://medium.com/expedia-group-tech/software-architectural-patterns-in-data-engineering-5d3bf22106a0?source=rss----38998a53046f---4",
    "date": "May 24, 2022",
    "imageUrl": "https://cdn-images-1.medium.com/max/1024/1*W7tEmEyyq49JmkZbZmHHeg.jpeg"
  },
  {
    "title": "Working around Datadog’s cardinality limitations",
    "creator": "Lorenzo Dell'Arciprete",
    "link": "https://medium.com/expedia-group-tech/working-around-datadogs-cardinality-limitations-be2f9a69612a?source=rss----38998a53046f---4",
    "date": "May 10, 2022",
    "imageUrl": "https://cdn-images-1.medium.com/max/1024/1*PngOUPImGBJkDHuXeisijw.jpeg"
  }
]